CHANGELOG.rst
CONTRIBUTING.rst
LICENSE
MANIFEST.in
README.rst
REQUIREMENTS
SUPPORT.rst
pyproject.toml
docs/Makefile
docs/REQUIREMENTS.txt
docs/about.rst
docs/api.rst
docs/conf.py
docs/extras.rst
docs/faqs.rst
docs/how-to-write.rst
docs/index.rst
docs/install.rst
docs/jax-tips.rst
docs/latex_index.rst
docs/make.bat
docs/quickstart.rst
docs/refs.rst
docs/dev-guide/contributing.rst
docs/dev-guide/modules.rst
docs/dev-guide/release-notes.rst
docs/dev-guide/release-proc.rst
docs/img/algorithm-flowchart.png
docs/img/des-obj-space.png
docs/img/des-sim-obj-space.png
docs/img/icon-ParMOO.png
docs/img/icon-ParMOO.svg
docs/img/icon-ParMOO_space.png
docs/img/logo-ParMOO.png
docs/img/logo-ParMOO.svg
docs/img/logo-ParMOO_white.png
docs/img/moop-uml.png
docs/img/moop-uml.svg
docs/img/moop.uml
docs/img/parmoo_movie.gif
docs/modules/acquisitions.rst
docs/modules/class_api.rst
docs/modules/constraints.rst
docs/modules/databases.rst
docs/modules/dev_tools.rst
docs/modules/dtlz.rst
docs/modules/embeddings.rst
docs/modules/libe.rst
docs/modules/libraries.rst
docs/modules/moop.rst
docs/modules/objectives.rst
docs/modules/optimizers.rst
docs/modules/searches.rst
docs/modules/simulations.rst
docs/modules/surrogates.rst
docs/modules/util.rst
docs/modules/viz.rst
docs/tutorials/basic-tutorials.rst
docs/tutorials/libe-tutorial.rst
docs/tutorials/local_method.rst
examples/Makefile
examples/advanced_ex.out
examples/advanced_ex.py
examples/checkpointing.out
examples/checkpointing.py
examples/libe_basic_ex.out
examples/libe_basic_ex.py
examples/local_method.csv
examples/local_method.jpeg
examples/local_method.py
examples/named_var_ex.out
examples/named_var_ex.py
examples/precomputed_data.out
examples/precomputed_data.py
examples/quickstart.jpeg
examples/quickstart.out
examples/quickstart.py
parmoo/__init__.py
parmoo/version.py
parmoo.egg-info/PKG-INFO
parmoo.egg-info/SOURCES.txt
parmoo.egg-info/dependency_links.txt
parmoo.egg-info/requires.txt
parmoo.egg-info/top_level.txt
parmoo/acquisitions/__init__.py
parmoo/acquisitions/acquisition_function.py
parmoo/acquisitions/chebyshev.py
parmoo/acquisitions/epsilon_constraint.py
