Metadata-Version: 2.4
Name: parmoo
Version: 0.5.0
Summary: Python library for parallel multiobjective simulation optimization
Author: Tyler H. Chang, Stefan M. Wild
Maintainer-email: ParMOO Developers <parmoo@lbl.gov>
License-Expression: BSD-3-Clause
Project-URL: Homepage, https://github.com/parmoo/parmoo
Project-URL: Source, https://github.com/parmoo/parmoo
Project-URL: Issues, https://github.com/parmoo/parmoo/issues
Classifier: Development Status :: 4 - Beta
Classifier: Intended Audience :: Developers
Classifier: Intended Audience :: Science/Research
Classifier: Natural Language :: English
Classifier: Operating System :: POSIX :: Linux
Classifier: Operating System :: Unix
Classifier: Operating System :: MacOS
Classifier: Programming Language :: Python :: 3
Classifier: Programming Language :: Python :: 3.9
Classifier: Programming Language :: Python :: 3.10
Classifier: Programming Language :: Python :: 3.11
Classifier: Programming Language :: Python :: 3.12
Classifier: Programming Language :: Python :: Implementation :: CPython
Classifier: Topic :: Scientific/Engineering
Classifier: Topic :: Software Development :: Libraries :: Python Modules
Requires-Python: >=3.9
License-File: LICENSE
Requires-Dist: jax[cpu]
Requires-Dist: numpy
Requires-Dist: scipy
Requires-Dist: pandas
Provides-Extra: extras
Requires-Dist: libensemble; extra == "extras"
Requires-Dist: plotly; extra == "extras"
Requires-Dist: dash; extra == "extras"
Requires-Dist: kaleido; extra == "extras"
Provides-Extra: docs
Requires-Dist: sphinx; extra == "docs"
Requires-Dist: sphinxcontrib.bibtex; extra == "docs"
Requires-Dist: sphinx_rtd_theme; extra == "docs"
Requires-Dist: sphinx-design; extra == "docs"
Provides-Extra: tests
Requires-Dist: pytest; extra == "tests"
Requires-Dist: pytest-cov; extra == "tests"
Requires-Dist: pyspelling; extra == "tests"
Requires-Dist: flake8; extra == "tests"
Requires-Dist: flake8-pyproject; extra == "tests"
Dynamic: license-file
